{
    "sourceFile": "docs/tutorial/adding-a-datasource.md",
    "activeCommit": 0,
    "commits": [
        {
            "activePatchIndex": 0,
            "patches": [
                {
                    "date": 1656582811807,
                    "content": "Index: \n===================================================================\n--- \n+++ \n"
                }
            ],
            "date": 1656582811807,
            "name": "Commit-0",
            "content": "---\nid: adding-a-datasource\ntitle: Adding a data source\n---\n\n# Adding a data source\n\n:::tip\nThe data sources are created on app level and not on workspace level.\n:::\n\n**Datasource manager** is on the left-sidebar of the app builder. To add a new data source, click on the `Add datasource` button.\n\n<div style={{textAlign: 'center'}}>\n\n![Insight - Tutorial - Adding a data source](/img/tutorial/adding-datasource/add-datasource.png)\n\n</div>\n\nYou will be prompted to select the data source that you wish to add. Let's select PostgreSQL for this tutorial. You will then need to provide the credentials of your PostgreSQL database. The fields that are marked as `encrypted` will be encrypted before saving to Insight's database. \n\n<div style={{textAlign: 'center'}}>\n\n![Insight - Tutorial - Adding a data source](/img/tutorial/adding-datasource/datasources.png)\n\n</div>\n\nThe name of the data source must be unique (within the app) and can be changed by clicking on the data source name at the top of the prompt. Click on `Test Connection` button to verify the connection, this might take a couple of minutes. Once verified, save the data source. \n\n:::tip\nIf you are using Insight cloud and if your data source is not publicly accessible, please white-list our IP address ( shown while creating a new data source ).\n:::\n\n<div style={{textAlign: 'center'}}>\n\n![Insight - Tutorial - Adding a data source](/img/tutorial/adding-datasource/postgres.png)\n\n</div>"
        }
    ]
}